{
    "name": "Itx-security",
    "models": [
        {
            "model": "bullet",
            "type": "FFMPEG",
            "protocol": "rtsp://",
            "url": "/live/main"
        },
        {
            "model": "dddd",
            "type": "FFMPEG",
            "protocol": "rtsp://",
            "url": "/live/main"
        },
        {
            "model": "IND2",
            "type": "FFMPEG",
            "protocol": "rtsp://",
            "url": "/live/main"
        },
        {
            "model": "KCEZB",
            "type": "FFMPEG",
            "protocol": "rtsp://",
            "url": "/live/main"
        },
        {
            "model": "NCD-2003PRH",
            "type": "FFMPEG",
            "protocol": "rtsp://",
            "url": "/live/main"
        },
        {
            "model": "NMB2300PR",
            "type": "FFMPEG",
            "protocol": "rtsp://",
            "url": "/live/main"
        },
        {
            "model": "RB300",
            "type": "FFMPEG",
            "protocol": "rtsp://",
            "url": "/live/main"
        },
        {
            "model": "IPDM844",
            "type": "FFMPEG",
            "protocol": "rtsp://",
            "url": "/cam/realmonitor?channel=1&subtype=00&authbasic=[AUTH]"
        },
        {
            "model": "NCD-2003PR2003PR",
            "type": "FFMPEG",
            "protocol": "rtsp://",
            "url": "/live/second"
        }
    ]
}