{
    "name": "Roline",
    "models": [
        {
            "model": "RBOF1-1",
            "type": "FFMPEG",
            "protocol": "rtsp://",
            "url": "/Streaming/Channels/101"
        },
        {
            "model": "RBOF4-1",
            "type": "FFMPEG",
            "protocol": "rtsp://",
            "url": "/Streaming/Channels/101"
        },
        {
            "model": "RBOV2-1",
            "type": "FFMPEG",
            "protocol": "rtsp://",
            "url": "/Streaming/Channels/101"
        },
        {
            "model": "RCIF3-1W",
            "type": "FFMPEG",
            "protocol": "rtsp://",
            "url": "/Streaming/Channels/101"
        },
        {
            "model": "rd0f2",
            "type": "FFMPEG",
            "protocol": "rtsp://",
            "url": "/Streaming/Channels/101"
        },
        {
            "model": "RDOF4-1",
            "type": "FFMPEG",
            "protocol": "rtsp://",
            "url": "/Streaming/Channels/101"
        },
        {
            "model": "RDOF2-1W",
            "type": "FFMPEG",
            "protocol": "rtsp://",
            "url": "/Streaming/Channels/1"
        }
    ]
}