{
    "name": "Zyxel",
    "models": [
        {
            "model": "2605-N",
            "type": "VLC",
            "protocol": "rtsp://",
            "url": "/medias2"
        },
        {
            "model": "4605",
            "type": "VLC",
            "protocol": "rtsp://",
            "url": "/medias2"
        },
        {
            "model": "IPC-3605N",
            "type": "VLC",
            "protocol": "rtsp://",
            "url": "/medias2"
        },
        {
            "model": "IPC36xx/46xx",
            "type": "VLC",
            "protocol": "rtsp://",
            "url": "/medias2"
        },
        {
            "model": "IPC-4605N",
            "type": "VLC",
            "protocol": "rtsp://",
            "url": "/medias2"
        }
    ]
}